mani/__init__.py
mani/domain/__init__.py
mani/domain/cqrs/__init__.py
mani/domain/cqrs/effects.py
mani/domain/cqrs/bus/__init__.py
mani/domain/cqrs/bus/bus_handler_failed.py
mani/domain/cqrs/bus/command_bus.py
mani/domain/cqrs/bus/effect_handler.py
mani/domain/cqrs/bus/event_bus.py
mani/domain/cqrs/bus/exceptions.py
mani/domain/cqrs/bus/query_bus.py
mani/domain/cqrs/bus/query_handler.py
mani/domain/cqrs/bus/state_management/__init__.py
mani/domain/cqrs/bus/state_management/effect_to_state_mapping.py
mani/domain/model/__init__.py
mani/domain/model/modules.py
mani/domain/model/application/__init__.py
mani/domain/model/application/domain_application.py
mani/domain/model/application/net_config.py
mani/domain/model/identifiable/__init__.py
mani/domain/model/identifiable/identifiable_entity.py
mani/domain/model/identifiable/identifier.py
mani/domain/model/repository/__init__.py
mani/domain/model/repository/repository.py
mani/infrastructure/__init__.py
mani/infrastructure/domain/__init__.py
mani/infrastructure/domain/cqrs/__init__.py
mani/infrastructure/domain/cqrs/cqrs_module.py
mani/infrastructure/domain/cqrs/bus/__init__.py
mani/infrastructure/domain/cqrs/bus/asynchronous_bus.py
mani/infrastructure/domain/cqrs/bus/command_bus_facade.py
mani/infrastructure/domain/cqrs/bus/event_bus_facade.py
mani/infrastructure/domain/cqrs/bus/local_asynchronous_bus.py
mani/infrastructure/domain/cqrs/bus/local_synchronous_bus.py
mani/infrastructure/domain/cqrs/bus/local_synchronous_query_bus.py
mani/infrastructure/domain/cqrs/bus/build_effect_handlers/__init__.py
mani/infrastructure/domain/cqrs/bus/build_effect_handlers/asynchronous_class.py
mani/infrastructure/domain/cqrs/bus/build_effect_handlers/state_managing_effect_handler.py
mani/infrastructure/domain/cqrs/bus/build_effect_handlers/synchronous_class.py
mani/infrastructure/domain/cqrs/bus/build_effect_handlers/synchronous_state_managing_effect_handler.py
mani/infrastructure/domain/model/__init__.py
mani_fwk-0.0.2.dist-info/METADATA
mani_fwk-0.0.2.dist-info/WHEEL
mani_fwk-0.0.2.dist-info/licenses/LICENSE
mani_fwk-0.0.2.dist-info/RECORD
