Metadata-Version: 2.1
Name: mani-fwk
Version: 0.0.2
Summary: A simple framework for building complex web applications.
Project-URL: Homepage, https://github.com/jvalduvieco/mani/sampleproject
Project-URL: Bug Tracker, https://github.com/jvalduvieco/mani/issues
Author-email: Joan Valduvieco <jvalduvieco@gmail.com>
License-File: LICENSE
Classifier: Environment :: Web Environment
Classifier: Intended Audience :: Developers
Classifier: License :: OSI Approved :: MIT License
Classifier: Operating System :: OS Independent
Classifier: Programming Language :: Python
Classifier: Programming Language :: Python :: 3
Classifier: Topic :: Software Development :: Libraries :: Application Frameworks
Requires-Python: >=3.7
Requires-Dist: injector==0.20.1
Requires-Dist: plum-dispatch==1.7.4
Requires-Dist: uuid==1.30
